logdeleter/LogDeleter-1.py
logdeleter/LogDeleter.py
logdeleter/__init__-1.py
logdeleter/__init__.py
logdeleter/clusterLogDeleter-1.py
logdeleter/clusterLogDeleter.py
logdeleter-1.0.0.dist-info/LICENSE.txt
logdeleter-1.0.0.dist-info/METADATA
logdeleter-1.0.0.dist-info/WHEEL
logdeleter-1.0.0.dist-info/top_level.txt
logdeleter-1.0.0.dist-info/RECORD
